hyperlight/__init__.py
hyperlight/convert.py
hyperlight/find.py
hyperlight/hypernet/__init__.py
hyperlight/hypernet/encoding.py
hyperlight/hypernet/initialization.py
hyperlight/hypernet/model.py
hyperlight/nn/__init__.py
hyperlight/nn/container.py
hyperlight/nn/layers.py
hyperlight/nn/module.py
hyperlight/nn/xparam.py
hyperlight-0.0.5.dist-info/LICENSE
hyperlight-0.0.5.dist-info/METADATA
hyperlight-0.0.5.dist-info/WHEEL
hyperlight-0.0.5.dist-info/RECORD
