Metadata-Version: 2.1
Name: hyperlight
Version: 0.0.5
Summary: Hyperlight is a Pytorch hypernetwork framework with a streamlined API
Home-page: https://github.com/JJGO/hyperlight
License: Apache-2.0
Keywords: hyperlight,pytorch,hypernetworks,deep learning
Author: Jose Javier Gonzalez Ortiz
Author-email: josejg@mit.edu
Requires-Python: >=3.7,<4.0
Classifier: Intended Audience :: Developers
Classifier: Intended Audience :: Science/Research
Classifier: License :: OSI Approved :: Apache Software License
Classifier: Programming Language :: Python :: 3
Classifier: Programming Language :: Python :: 3.7
Classifier: Programming Language :: Python :: 3.8
Classifier: Programming Language :: Python :: 3.9
Classifier: Programming Language :: Python :: 3.10
Classifier: Programming Language :: Python :: 3.11
Classifier: Programming Language :: Python :: 3
Classifier: Programming Language :: Python :: 3.10
Classifier: Programming Language :: Python :: 3.8
Classifier: Programming Language :: Python :: 3.9
Requires-Dist: torch (>=1.10,<3)
Project-URL: Documentation, https://github.com/JJGO/hyperlight
